poe_terminal_chat/__init__.py
poe_terminal_chat/command_line.py
poe_terminal_chat/poeterminal.py
poe_terminal_chat/utils.py
poe_terminal_chat-0.0.7.dist-info/LICENSE
poe_terminal_chat-0.0.7.dist-info/METADATA
poe_terminal_chat-0.0.7.dist-info/WHEEL
poe_terminal_chat-0.0.7.dist-info/entry_points.txt
poe_terminal_chat-0.0.7.dist-info/top_level.txt
poe_terminal_chat-0.0.7.dist-info/RECORD
